<?xml version="1.0" encoding="UTF-8"?>
<objects serializationModel="Studio.02.02.00">
	<object class="AudioFile" id="{c444fcd6-4dee-495f-896d-b8bc8d0b512a}">
		<property name="assetPath">
			<value>PlayerParty/Abilities/Taunt_Tank.wav</value>
		</property>
		<property name="frequencyInKHz">
			<value>44.0999985</value>
		</property>
		<property name="channelCount">
			<value>2</value>
		</property>
		<property name="length">
			<value>1.6071428571428572</value>
		</property>
		<relationship name="masterAssetFolder">
			<destination>{ffc8284e-fe15-423d-846c-6e671f226029}</destination>
		</relationship>
	</object>
</objects>
